imputing/__init__.py
imputing/utils.py
imputing/imputation/__init__.py
imputing/imputation/imputation.py
imputing/missingness/__init__.py
imputing/missingness/missingness.py
imputing-0.1.0.dist-info/LICENSE
imputing-0.1.0.dist-info/METADATA
imputing-0.1.0.dist-info/WHEEL
imputing-0.1.0.dist-info/top_level.txt
imputing-0.1.0.dist-info/RECORD
